ariel_srt/__init__.py
ariel_srt/Alignment.py
ariel_srt/Landmark.py
ariel_srt/Transfer.py
ariel_srt-0.1.4.dist-info/LICENSE
ariel_srt-0.1.4.dist-info/METADATA
ariel_srt-0.1.4.dist-info/WHEEL
ariel_srt-0.1.4.dist-info/RECORD
