Metadata-Version: 2.3
Name: ariel-srt
Version: 0.1.4
Summary: 
Author: Yang Wanshuo
Author-email: yangwanshuo@example.com
Requires-Python: >=3.9
Classifier: Programming Language :: Python :: 3
Classifier: Programming Language :: Python :: 3.9
Classifier: Programming Language :: Python :: 3.10
Classifier: Programming Language :: Python :: 3.11
Classifier: Programming Language :: Python :: 3.12
Classifier: Programming Language :: Python :: 3.13
Requires-Dist: gpytorch (>=1.11.0)
Requires-Dist: numpy (>=1.26.0)
Requires-Dist: scikit-learn (>=1.3.0)
Requires-Dist: thinplate (>=1.0.0)
Requires-Dist: torch (>=2.3.1)
